noisily/__init__.py
noisily/noise.so
noisily-0.0.2.dist-info/DESCRIPTION.rst
noisily-0.0.2.dist-info/METADATA
noisily-0.0.2.dist-info/RECORD
noisily-0.0.2.dist-info/WHEEL
noisily-0.0.2.dist-info/metadata.json
noisily-0.0.2.dist-info/top_level.txt
