Metadata-Version: 2.0
Name: noisily
Version: 0.0.2
Summary: UNKNOWN
Home-page: https://github.com/tocubed/noisily
Author: Priyank Patel
Author-email: tocubed@gmail.com
License: MIT
Platform: UNKNOWN
Requires-Dist: Cython (>=0.25.0)
Requires-Dist: numpy (>=1.11.0)
Requires-Dist: setuptools (>=18.0)
